odoo/addons/currency_monthly_rate/README.rst
odoo/addons/currency_monthly_rate/__init__.py
odoo/addons/currency_monthly_rate/__manifest__.py
odoo/addons/currency_monthly_rate/models/__init__.py
odoo/addons/currency_monthly_rate/models/res_currency.py
odoo/addons/currency_monthly_rate/security/ir.model.access.csv
odoo/addons/currency_monthly_rate/security/res_groups.xml
odoo/addons/currency_monthly_rate/tests/__init__.py
odoo/addons/currency_monthly_rate/tests/test_currency_monthly_rate.py
odoo/addons/currency_monthly_rate/views/res_currency.xml
odoo11_addon_currency_monthly_rate-11.0.1.0.0.dist-info/DESCRIPTION.rst
odoo11_addon_currency_monthly_rate-11.0.1.0.0.dist-info/METADATA
odoo11_addon_currency_monthly_rate-11.0.1.0.0.dist-info/RECORD
odoo11_addon_currency_monthly_rate-11.0.1.0.0.dist-info/WHEEL
odoo11_addon_currency_monthly_rate-11.0.1.0.0.dist-info/metadata.json
odoo11_addon_currency_monthly_rate-11.0.1.0.0.dist-info/top_level.txt
